flowcard/__init__.py
flowcard/base.py
flowcard/component.py
flowcard-0.1.0.dist-info/METADATA
flowcard-0.1.0.dist-info/WHEEL
flowcard-0.1.0.dist-info/licenses/LICENSE
flowcard-0.1.0.dist-info/RECORD
