Metadata-Version: 2.4
Name: flowcard
Version: 0.1.0
Summary: Transform your code workflow into comprehensive documentation
Project-URL: Homepage, https://github.com/RemyCocq/flowcard
Project-URL: Repository, https://github.com/RemyCocq/flowcard
Author: RemyCocq
License: MIT
License-File: LICENSE
Keywords: card,html,markdown
Requires-Python: >=3.11
Requires-Dist: jinja2>=3.1.0
Requires-Dist: markdown>=3.8
Requires-Dist: matplotlib>=3.10.3
Requires-Dist: numpy>=2.2.6
Requires-Dist: pillow>=11.2.1
Requires-Dist: python-magic>=0.4.27
